helper/__init__.py
helper/convertor.py
helper/exif_read.py
helper/generator.py
helper/geo.py
helper/handler.py
helper/logger.py
helper/rule.py
helper/util.py
helper_mapilio-1.1.37.dist-info/METADATA
helper_mapilio-1.1.37.dist-info/WHEEL
helper_mapilio-1.1.37.dist-info/top_level.txt
helper_mapilio-1.1.37.dist-info/RECORD
