Metadata-Version: 2.1
Name: helper-mapilio
Version: 1.1.37
Summary: Mapilio Helper Library
Home-page: https://github.com/mapilio/helper.git
Author: Mapilio - Ozcan Durak & M.Can VARER
Author-email: ozcan@visiosoft.com.tr
License: MIT
Project-URL: Bug Reports, https://github.com/mapilio/helper/issues
Project-URL: Say Thanks!, https://mapilio.com/#contact
Project-URL: Source, https://github.com/mapilio/helper/
Requires-Python: >=3.6, <4
Requires-Dist: trianglesolver (==1.2)
Requires-Dist: opencv-python (==4.6.0.66)
Requires-Dist: addict (==2.4.0)
